pystatsv1/__init__.py
pystatsv1/__main__.py
pystatsv1/cli.py
pystatsv1/console.py
pystatsv1/docs_helper.py
pystatsv1/paths.py
pystatsv1/assets/__init__.py
pystatsv1/assets/ledgerlab_ch01_seed123.zip
pystatsv1/assets/nso_v1_seed123.zip
pystatsv1/assets/workbook_starter.zip
pystatsv1/assets/workbook_track_d.zip
pystatsv1/docs/pystatsv1.pdf
pystatsv1/trackd/__init__.py
pystatsv1/trackd/_errors.py
pystatsv1/trackd/_types.py
pystatsv1/trackd/byod.py
pystatsv1/trackd/contracts.py
pystatsv1/trackd/csvio.py
pystatsv1/trackd/etl.py
pystatsv1/trackd/loaders.py
pystatsv1/trackd/mpl_compat.py
pystatsv1/trackd/recon.py
pystatsv1/trackd/reporting_style.py
pystatsv1/trackd/schema.py
pystatsv1/trackd/validate.py
pystatsv1/trackd/adapters/__init__.py
pystatsv1/trackd/adapters/base.py
pystatsv1/trackd/adapters/core_gl.py
pystatsv1/trackd/adapters/gnucash_gl.py
pystatsv1/trackd/adapters/mapping.py
pystatsv1-0.22.4.dist-info/licenses/LICENSE
pystatsv1-0.22.4.dist-info/METADATA
pystatsv1-0.22.4.dist-info/WHEEL
pystatsv1-0.22.4.dist-info/entry_points.txt
pystatsv1-0.22.4.dist-info/top_level.txt
pystatsv1-0.22.4.dist-info/RECORD
