Metadata-Version: 2.4
Name: pystatsv1
Version: 0.22.4
Summary: PyStatsV1: applied statistics labs in Python.
Author: PyStatsV1 contributors
License-Expression: MIT
Project-URL: Homepage, https://github.com/pystatsv1/PyStatsV1
Project-URL: Documentation, https://pystatsv1.readthedocs.io
Project-URL: Source, https://github.com/pystatsv1/PyStatsV1
Project-URL: Issues, https://github.com/pystatsv1/PyStatsV1/issues
Project-URL: PyPI, https://pypi.org/project/pystatsv1/
Requires-Python: >=3.10
License-File: LICENSE
Requires-Dist: numpy>=1.24
Requires-Dist: pandas>=2.0
Requires-Dist: scipy>=1.10
Requires-Dist: statsmodels>=0.14
Requires-Dist: matplotlib>=3.8
Requires-Dist: pingouin>=0.5
Requires-Dist: scikit-learn>=1.3
Provides-Extra: workbook
Requires-Dist: pytest>=8.2; extra == "workbook"
Provides-Extra: dev
Requires-Dist: pytest>=8.2; extra == "dev"
Requires-Dist: ruff>=0.6; extra == "dev"
Requires-Dist: black>=24.0; extra == "dev"
Provides-Extra: docs
Requires-Dist: sphinx>=8.0; extra == "docs"
Requires-Dist: sphinx-rtd-theme>=2.0; extra == "docs"
Requires-Dist: myst-parser>=3.0; extra == "docs"
Dynamic: license-file
